hicml/DataStructures.py
hicml/DeploymentUtils.py
hicml/NonMaxSuppression.py
hicml/Oracle.py
hicml/PredictionHandler.py
hicml/StrawMLTools.py
hicml/__init__.py
hicml-0.2.2.dist-info/METADATA
hicml-0.2.2.dist-info/WHEEL
hicml-0.2.2.dist-info/top_level.txt
hicml-0.2.2.dist-info/RECORD
