Metadata-Version: 2.1
Name: hicml
Version: 0.2.2
Summary: ML tools for analyzing Hi-C data
Home-page: https://github.com/dgound/hic-ml
Author: Muhammad Shamim, Alyssa Blackburn, Dimos Gkountaroulis
Author-email: aidenlab@bcm.edu
License: MIT
Keywords: Hi-C,3D genomics,Chromatin,ML
Platform: UNKNOWN
Requires-Python: >3.3
Requires-Dist: numpy
Requires-Dist: scipy
Requires-Dist: keras
Requires-Dist: tensorflow
Requires-Dist: hic-straw
